{
  "type": "FeatureCollection",
  "name": "Sample community POIs",
  "features": [
    {
      "type": "Feature",
      "properties": {
        "name": "City Arts Cooperative",
        "category": "arts_centre",
        "subtype": "community_culture",
        "opening_hours": "Mo-Fr 10:00-18:00",
        "rating": 4.6,
        "rating_count": 127,
        "id": "open-poi-001"
      },
      "geometry": {
        "type": "Point",
        "coordinates": [-73.9833, 40.7539]
      }
    },
    {
      "type": "Feature",
      "properties": {
        "name": "Midtown Public Library",
        "category": "library",
        "subtype": "public_service",
        "opening_hours": "Mo-Sa 09:00-20:00; Su 10:00-16:00",
        "rating": 4.8,
        "rating_count": 312,
        "id": "open-poi-002"
      },
      "geometry": {
        "type": "Point",
        "coordinates": [-73.9812, 40.7554]
      }
    }
  ]
}
